rocket_welder_sdk/__init__.py
rocket_welder_sdk/binary_frame_reader.py
rocket_welder_sdk/binary_frame_writer.py
rocket_welder_sdk/bytes_size.py
rocket_welder_sdk/confidence.py
rocket_welder_sdk/connection_string.py
rocket_welder_sdk/controllers.py
rocket_welder_sdk/delta_frame.py
rocket_welder_sdk/frame_metadata.py
rocket_welder_sdk/gst_metadata.py
rocket_welder_sdk/keypoints_protocol.py
rocket_welder_sdk/opencv_controller.py
rocket_welder_sdk/periodic_timer.py
rocket_welder_sdk/py.typed
rocket_welder_sdk/rocket_welder_client.py
rocket_welder_sdk/segmentation_result.py
rocket_welder_sdk/session_id.py
rocket_welder_sdk/varint.py
rocket_welder_sdk/external_controls/__init__.py
rocket_welder_sdk/external_controls/contracts.py
rocket_welder_sdk/external_controls/contracts_old.py
rocket_welder_sdk/graphics/__init__.py
rocket_welder_sdk/graphics/layer_canvas.py
rocket_welder_sdk/graphics/protocol.py
rocket_welder_sdk/graphics/rgb_color.py
rocket_welder_sdk/graphics/stage.py
rocket_welder_sdk/graphics/vector_graphics_encoder.py
rocket_welder_sdk/high_level/__init__.py
rocket_welder_sdk/high_level/client.py
rocket_welder_sdk/high_level/connection_strings.py
rocket_welder_sdk/high_level/data_context.py
rocket_welder_sdk/high_level/frame_sink_factory.py
rocket_welder_sdk/high_level/schema.py
rocket_welder_sdk/high_level/transport_protocol.py
rocket_welder_sdk/transport/__init__.py
rocket_welder_sdk/transport/frame_sink.py
rocket_welder_sdk/transport/frame_source.py
rocket_welder_sdk/transport/stream_transport.py
rocket_welder_sdk/transport/tcp_transport.py
rocket_welder_sdk/transport/unix_socket_transport.py
rocket_welder_sdk/transport/websocket_transport.py
rocket_welder_sdk/ui/__init__.py
rocket_welder_sdk/ui/controls.py
rocket_welder_sdk/ui/icons.py
rocket_welder_sdk/ui/ui_events_projection.py
rocket_welder_sdk/ui/ui_service.py
rocket_welder_sdk/ui/value_types.py
rocket_welder_sdk-1.1.47.dist-info/METADATA
rocket_welder_sdk-1.1.47.dist-info/WHEEL
rocket_welder_sdk-1.1.47.dist-info/top_level.txt
rocket_welder_sdk-1.1.47.dist-info/RECORD
