Metadata-Version: 2.4
Name: rocket-welder-sdk
Version: 1.1.47
Summary: High-performance video streaming SDK for RocketWelder services using ZeroBuffer IPC
Home-page: https://github.com/modelingevolution/rocket-welder-sdk
Author: ModelingEvolution
Author-email: ModelingEvolution <info@modelingevolution.com>
Maintainer-email: ModelingEvolution <info@modelingevolution.com>
License: MIT
Project-URL: Homepage, https://github.com/modelingevolution/rocket-welder-sdk
Project-URL: Repository, https://github.com/modelingevolution/rocket-welder-sdk.git
Project-URL: Issues, https://github.com/modelingevolution/rocket-welder-sdk/issues
Keywords: video,streaming,gstreamer,ipc,shared-memory,zerobuffer,computer-vision
Classifier: Development Status :: 4 - Beta
Classifier: Intended Audience :: Developers
Classifier: Topic :: Multimedia :: Video
Classifier: Topic :: Software Development :: Libraries :: Python Modules
Classifier: License :: OSI Approved :: MIT License
Classifier: Programming Language :: Python :: 3
Classifier: Programming Language :: Python :: 3.8
Classifier: Programming Language :: Python :: 3.9
Classifier: Programming Language :: Python :: 3.10
Classifier: Programming Language :: Python :: 3.11
Classifier: Programming Language :: Python :: 3.12
Classifier: Operating System :: OS Independent
Classifier: Typing :: Typed
Requires-Python: >=3.8
Requires-Dist: numpy>=1.20.0
Requires-Dist: opencv-python>=4.5.0
Requires-Dist: zerobuffer-ipc>=1.1.17
Requires-Dist: pydantic>=2.5.0
Requires-Dist: py-micro-plumberd>=0.1.8
Requires-Dist: typing-extensions>=4.0.0
Provides-Extra: dev
Requires-Dist: pytest>=7.0; extra == "dev"
Requires-Dist: pytest-cov>=4.0; extra == "dev"
Requires-Dist: pytest-asyncio>=0.21; extra == "dev"
Requires-Dist: black>=22.0; extra == "dev"
Requires-Dist: mypy>=1.0; extra == "dev"
Requires-Dist: ruff>=0.1.0; extra == "dev"
Requires-Dist: types-setuptools; extra == "dev"
Dynamic: author
Dynamic: home-page
Dynamic: requires-python
